lintdata/__init__.py
lintdata/accessor.py
lintdata/checks.py
lintdata/parallel.py
lintdata/py.typed
lintdata/report_formatter.py
lintdata-1.1.0.dist-info/METADATA
lintdata-1.1.0.dist-info/WHEEL
lintdata-1.1.0.dist-info/licenses/LICENSE
lintdata-1.1.0.dist-info/RECORD
