Metadata-Version: 2.4
Name: lintdata
Version: 1.1.0
Summary: A "linter" for pandas DataFrames to automate data quality audits.
Project-URL: Homepage, https://github.com/patelheet30/lintdata
Project-URL: Documentation, https://lintdata.patelheet.com
Project-URL: Repository, https://github.com/patelheet30/lintdata
Project-URL: Issues, https://github.com/patelheet30/lintdata/issues
Author-email: Heet Patel <heetkpatel30@gmail.com>
License: Copyright (c) 2025 Heet Patel
License-File: LICENSE
Classifier: Development Status :: 5 - Production/Stable
Classifier: Intended Audience :: Developers
Classifier: License :: OSI Approved :: MIT License
Classifier: Operating System :: OS Independent
Classifier: Programming Language :: Python :: 3.13
Classifier: Topic :: Software Development :: Libraries
Classifier: Topic :: Software Development :: Quality Assurance
Requires-Python: >=3.13
Requires-Dist: pandas>=2.3.3
Provides-Extra: joblib
Requires-Dist: joblib>=1.5.2; extra == 'joblib'
